{
  "source": {
    "id": "SparshHospital",
    "name": "Sparsh Hospital",
    "lat": 13.0277298,
    "lng": 77.5428356
  },
  "destination": {
    "id": "SanjeeviniHospital",
    "name": "Sanjeevini Hospital",
    "lat": 12.982157,
    "lng": 77.598217
  },
  "cache_key": "420dcd60b9813a17af2bd160a2bc79fed3855e87d2829356aac9db2878956617",
  "calculated_at": 1751366522.0302494,
  "results": [
    {
      "algorithm": "A*",
      "time": 0.03345169999738573,
      "nodes": 1453,
      "distance": 10.108812083917556,
      "route": [
        [
          13.0274495,
          77.5434328
        ],
        [
          13.0272966,
          77.5436942
        ],
        [
          13.0270022,
          77.5435414
        ],
        [
          13.0267882,
          77.543901
        ],
        [
          13.0266639,
          77.5441183
        ],
        [
          13.0265475,
          77.5443205
        ],
        [
          13.02652,
          77.5443688
        ],
        [
          13.0264419,
          77.5445056
        ],
        [
          13.0262783,
          77.5447919
        ],
        [
          13.0261409,
          77.545034
        ],
        [
          13.0261054,
          77.5450986
        ],
        [
          13.0260108,
          77.545262
        ],
        [
          13.0249313,
          77.5471692
        ],
        [
          13.0247374,
          77.5475117
        ],
        [
          13.0247066,
          77.547572
        ],
        [
          13.0246136,
          77.5477353
        ],
        [
          13.0245653,
          77.5478201
        ],
        [
          13.0245012,
          77.5479328
        ],
        [
          13.0244568,
          77.5480082
        ],
        [
          13.0244128,
          77.548086
        ],
        [
          13.0243805,
          77.5481432
        ],
        [
          13.0242183,
          77.5484302
        ],
        [
          13.0241831,
          77.5484922
        ],
        [
          13.0241439,
          77.548561
        ],
        [
          13.0239562,
          77.5488912
        ],
        [
          13.0237829,
          77.5491463
        ],
        [
          13.0234939,
          77.5496389
        ],
        [
          13.0230509,
          77.5503516
        ],
        [
          13.0228045,
          77.5508058
        ],
        [
          13.0226969,
          77.5510277
        ],
        [
          13.0225022,
          77.5513199
        ],
        [
          13.0223589,
          77.5514832
        ],
        [
          13.0222094,
          77.5516361
        ],
        [
          13.0220275,
          77.5517794
        ],
        [
          13.0218485,
          77.5519049
        ],
        [
          13.0216343,
          77.552036
        ],
        [
          13.0210655,
          77.5523307
        ],
        [
          13.0197485,
          77.5530421
        ],
        [
          13.0195316,
          77.5531433
        ],
        [
          13.019371,
          77.5532075
        ],
        [
          13.0192211,
          77.5532574
        ],
        [
          13.0190504,
          77.553303
        ],
        [
          13.0178943,
          77.5535869
        ],
        [
          13.0177693,
          77.5536176
        ],
        [
          13.0172412,
          77.5537435
        ],
        [
          13.0169446,
          77.553794
        ],
        [
          13.0166951,
          77.5538253
        ],
        [
          13.0162882,
          77.5538613
        ],
        [
          13.0161467,
          77.5538709
        ],
        [
          13.0160489,
          77.5538828
        ],
        [
          13.0159637,
          77.5539138
        ],
        [
          13.0159,
          77.5539575
        ],
        [
          13.0158471,
          77.5540122
        ],
        [
          13.0156651,
          77.5542035
        ],
        [
          13.015608,
          77.5542919
        ],
        [
          13.015547,
          77.5544046
        ],
        [
          13.0155177,
          77.5544877
        ],
        [
          13.0155055,
          77.5545382
        ],
        [
          13.0154946,
          77.5545832
        ],
        [
          13.0154865,
          77.554739
        ],
        [
          13.0155011,
          77.5549491
        ],
        [
          13.0155207,
          77.555063
        ],
        [
          13.0155344,
          77.555143
        ],
        [
          13.0155858,
          77.5552981
        ],
        [
          13.0156628,
          77.5554694
        ],
        [
          13.0157848,
          77.5556735
        ],
        [
          13.0159736,
          77.5559295
        ],
        [
          13.0161611,
          77.5561139
        ],
        [
          13.0162957,
          77.5562294
        ],
        [
          13.0164109,
          77.5563145
        ],
        [
          13.0166404,
          77.5564571
        ],
        [
          13.0166867,
          77.5564859
        ],
        [
          13.0167961,
          77.5565567
        ],
        [
          13.0174983,
          77.5569446
        ],
        [
          13.0177664,
          77.5570926
        ],
        [
          13.0178893,
          77.5571548
        ],
        [
          13.0184313,
          77.5574596
        ],
        [
          13.0185332,
          77.5575266
        ],
        [
          13.0186116,
          77.5576044
        ],
        [
          13.0186699,
          77.5576937
        ],
        [
          13.0186978,
          77.5577922
        ],
        [
          13.0187057,
          77.5578994
        ],
        [
          13.018696,
          77.5579995
        ],
        [
          13.0186665,
          77.5580845
        ],
        [
          13.0185241,
          77.5582556
        ],
        [
          13.0182515,
          77.5587301
        ],
        [
          13.0180601,
          77.5590569
        ],
        [
          13.0176671,
          77.5597027
        ],
        [
          13.0171281,
          77.5605923
        ],
        [
          13.0165773,
          77.5615849
        ],
        [
          13.016062,
          77.5625188
        ],
        [
          13.0151584,
          77.5640534
        ],
        [
          13.0147984,
          77.5645578
        ],
        [
          13.0142656,
          77.5654694
        ],
        [
          13.0139875,
          77.5659369
        ],
        [
          13.0133266,
          77.5670352
        ],
        [
          13.0130571,
          77.5675183
        ],
        [
          13.013001,
          77.5676212
        ],
        [
          13.0122894,
          77.5688249
        ],
        [
          13.0122527,
          77.5688989
        ],
        [
          13.012214,
          77.5689774
        ],
        [
          13.0122238,
          77.5690031
        ],
        [
          13.0122301,
          77.5690528
        ],
        [
          13.0122169,
          77.5691081
        ],
        [
          13.0121959,
          77.5691573
        ],
        [
          13.0121524,
          77.5692036
        ],
        [
          13.0120818,
          77.5692296
        ],
        [
          13.0120117,
          77.5692247
        ],
        [
          13.0119499,
          77.5692569
        ],
        [
          13.011836,
          77.5693433
        ],
        [
          13.0109449,
          77.57002
        ],
        [
          13.0105426,
          77.5703266
        ],
        [
          13.0105079,
          77.5703535
        ],
        [
          13.0102857,
          77.5705224
        ],
        [
          13.0102291,
          77.5705641
        ],
        [
          13.0101351,
          77.5706328
        ],
        [
          13.0099036,
          77.5708041
        ],
        [
          13.0098699,
          77.5708289
        ],
        [
          13.009736,
          77.5709276
        ],
        [
          13.0096469,
          77.5709952
        ],
        [
          13.009554,
          77.5710656
        ],
        [
          13.0094868,
          77.5711165
        ],
        [
          13.0093989,
          77.5711832
        ],
        [
          13.0093871,
          77.5711906
        ],
        [
          13.0092897,
          77.5712518
        ],
        [
          13.0092582,
          77.5712662
        ],
        [
          13.0090507,
          77.5713702
        ],
        [
          13.0086433,
          77.5716023
        ],
        [
          13.0086251,
          77.5716149
        ],
        [
          13.0086069,
          77.5716274
        ],
        [
          13.0085658,
          77.5716558
        ],
        [
          13.0084201,
          77.5718291
        ],
        [
          13.008372,
          77.571895
        ],
        [
          13.0080898,
          77.5722832
        ],
        [
          13.0079642,
          77.5724781
        ],
        [
          13.0078796,
          77.5726686
        ],
        [
          13.0078506,
          77.5727339
        ],
        [
          13.0078022,
          77.5728432
        ],
        [
          13.0076966,
          77.5732172
        ],
        [
          13.0076458,
          77.5734335
        ],
        [
          13.0076272,
          77.5737448
        ],
        [
          13.0076353,
          77.5740093
        ],
        [
          13.0077845,
          77.5750496
        ],
        [
          13.0078496,
          77.5755168
        ],
        [
          13.0078624,
          77.575827
        ],
        [
          13.0078165,
          77.5761149
        ],
        [
          13.0077453,
          77.5763443
        ],
        [
          13.0073895,
          77.5770197
        ],
        [
          13.0066148,
          77.5785548
        ],
        [
          13.006569,
          77.5786352
        ],
        [
          13.0065399,
          77.5786862
        ],
        [
          13.0065156,
          77.5787288
        ],
        [
          13.0064549,
          77.5788332
        ],
        [
          13.0063766,
          77.5787819
        ],
        [
          13.0062337,
          77.5787111
        ],
        [
          13.00616,
          77.5786822
        ],
        [
          13.0059044,
          77.5786426
        ],
        [
          13.0057777,
          77.5786155
        ],
        [
          13.0053365,
          77.5785545
        ],
        [
          13.0046946,
          77.5785479
        ],
        [
          13.0037278,
          77.5785544
        ],
        [
          13.0027908,
          77.5785508
        ],
        [
          13.0027204,
          77.5785515
        ],
        [
          13.0026289,
          77.5785125
        ],
        [
          13.002003,
          77.5784954
        ],
        [
          13.0018492,
          77.5784992
        ],
        [
          13.0016888,
          77.5784674
        ],
        [
          13.0013653,
          77.578423
        ],
        [
          13.0011523,
          77.5783923
        ],
        [
          13.001069,
          77.5783759
        ],
        [
          13.0009722,
          77.5783653
        ],
        [
          13.0008499,
          77.578346
        ],
        [
          13.0007936,
          77.5783291
        ],
        [
          13.000646,
          77.5782984
        ],
        [
          13.0004968,
          77.5782583
        ],
        [
          13.0004462,
          77.5782447
        ],
        [
          13.0003646,
          77.5782342
        ],
        [
          13.0001951,
          77.5782124
        ],
        [
          12.9999215,
          77.5781666
        ],
        [
          12.9998623,
          77.5781567
        ],
        [
          12.9997553,
          77.5781505
        ],
        [
          12.9994944,
          77.5781306
        ],
        [
          12.9992748,
          77.5781011
        ],
        [
          12.9991964,
          77.5783881
        ],
        [
          12.9991087,
          77.579517
        ],
        [
          12.9991005,
          77.5796505
        ],
        [
          12.9990706,
          77.580136
        ],
        [
          12.9990356,
          77.5807033
        ],
        [
          12.9990175,
          77.5813262
        ],
        [
          12.9991008,
          77.5816498
        ],
        [
          12.9991548,
          77.5818149
        ],
        [
          12.9993088,
          77.5824773
        ],
        [
          12.9993643,
          77.5828907
        ],
        [
          12.9993722,
          77.5830997
        ],
        [
          12.9993819,
          77.5834261
        ],
        [
          12.9993971,
          77.5836593
        ],
        [
          12.9993963,
          77.5838428
        ],
        [
          12.9993701,
          77.5838874
        ],
        [
          12.9992843,
          77.5839212
        ],
        [
          12.998628,
          77.5840779
        ],
        [
          12.9982312,
          77.5841593
        ],
        [
          12.9979322,
          77.5842105
        ],
        [
          12.9978612,
          77.5842288
        ],
        [
          12.9978131,
          77.584266
        ],
        [
          12.9978008,
          77.5843139
        ],
        [
          12.9978004,
          77.5844634
        ],
        [
          12.9977921,
          77.5847476
        ],
        [
          12.9977878,
          77.584791
        ],
        [
          12.9976358,
          77.5863097
        ],
        [
          12.9975599,
          77.5865735
        ],
        [
          12.997496,
          77.5867199
        ],
        [
          12.9974132,
          77.5868446
        ],
        [
          12.9968136,
          77.5875987
        ],
        [
          12.9965001,
          77.5880733
        ],
        [
          12.9962632,
          77.588492
        ],
        [
          12.9958439,
          77.5893578
        ],
        [
          12.9957733,
          77.5894726
        ],
        [
          12.995677,
          77.589556
        ],
        [
          12.9956077,
          77.5895917
        ],
        [
          12.9955008,
          77.5896469
        ],
        [
          12.9951975,
          77.5898089
        ],
        [
          12.9951985,
          77.5898575
        ],
        [
          12.9952303,
          77.5913512
        ],
        [
          12.9952304,
          77.5913653
        ],
        [
          12.9952307,
          77.5914194
        ],
        [
          12.9952556,
          77.5918525
        ],
        [
          12.9952241,
          77.5920953
        ],
        [
          12.9952094,
          77.5922088
        ],
        [
          12.9951219,
          77.5924738
        ],
        [
          12.9951057,
          77.5925255
        ],
        [
          12.9949713,
          77.5929899
        ],
        [
          12.9947867,
          77.5934047
        ],
        [
          12.994676,
          77.5936323
        ],
        [
          12.9946065,
          77.5937707
        ],
        [
          12.9945196,
          77.5939439
        ],
        [
          12.9944414,
          77.5940997
        ],
        [
          12.9944288,
          77.5941249
        ],
        [
          12.9943469,
          77.5942881
        ],
        [
          12.9941929,
          77.59457
        ],
        [
          12.9940681,
          77.5948065
        ],
        [
          12.9938659,
          77.5952008
        ],
        [
          12.9938766,
          77.5952679
        ],
        [
          12.9938574,
          77.5953141
        ],
        [
          12.9938275,
          77.5953827
        ],
        [
          12.9937568,
          77.5955811
        ],
        [
          12.9937411,
          77.5956617
        ],
        [
          12.9937407,
          77.5957328
        ],
        [
          12.9937589,
          77.5958002
        ],
        [
          12.9938143,
          77.5959199
        ],
        [
          12.9939264,
          77.5960106
        ],
        [
          12.9940162,
          77.5960929
        ],
        [
          12.994152,
          77.5962241
        ],
        [
          12.9941208,
          77.5963919
        ],
        [
          12.9940894,
          77.5965051
        ],
        [
          12.9940353,
          77.5966565
        ],
        [
          12.9938347,
          77.5967279
        ],
        [
          12.9936324,
          77.5968779
        ],
        [
          12.9933705,
          77.5971645
        ],
        [
          12.9931565,
          77.5975674
        ],
        [
          12.9930127,
          77.597813
        ],
        [
          12.9929827,
          77.5978644
        ],
        [
          12.9929147,
          77.5980113
        ],
        [
          12.9929069,
          77.5981589
        ],
        [
          12.9929356,
          77.5982957
        ],
        [
          12.9929014,
          77.5984316
        ],
        [
          12.9928809,
          77.5985098
        ],
        [
          12.9923015,
          77.6000075
        ],
        [
          12.9922893,
          77.6000414
        ],
        [
          12.9918412,
          77.5999249
        ],
        [
          12.9907397,
          77.599624
        ],
        [
          12.9907063,
          77.599613
        ],
        [
          12.9905185,
          77.5995661
        ],
        [
          12.9904351,
          77.5995369
        ],
        [
          12.9897683,
          77.5993038
        ],
        [
          12.9894026,
          77.599176
        ],
        [
          12.9883347,
          77.5988027
        ],
        [
          12.9875395,
          77.5985247
        ],
        [
          12.9873539,
          77.5984275
        ],
        [
          12.9870229,
          77.598274
        ],
        [
          12.9867013,
          77.5981458
        ],
        [
          12.9863163,
          77.5979931
        ],
        [
          12.9861562,
          77.5979295
        ],
        [
          12.9856695,
          77.5977364
        ],
        [
          12.9852024,
          77.597551
        ],
        [
          12.984566,
          77.5972588
        ],
        [
          12.9845528,
          77.5972528
        ],
        [
          12.9845305,
          77.5972423
        ],
        [
          12.9845003,
          77.5972273
        ],
        [
          12.9844235,
          77.5972837
        ],
        [
          12.984327,
          77.597199
        ],
        [
          12.9841797,
          77.5971128
        ],
        [
          12.9841563,
          77.5970901
        ],
        [
          12.983979,
          77.5971038
        ],
        [
          12.9837064,
          77.5971058
        ],
        [
          12.98364,
          77.5971063
        ],
        [
          12.9834359,
          77.5971078
        ],
        [
          12.9831307,
          77.5971101
        ],
        [
          12.9828705,
          77.5971408
        ],
        [
          12.9828464,
          77.5971431
        ],
        [
          12.9827271,
          77.5971513
        ],
        [
          12.9826708,
          77.5972842
        ],
        [
          12.9826053,
          77.5974734
        ],
        [
          12.9824663,
          77.597875
        ],
        [
          12.982415,
          77.5980314
        ],
        [
          12.9823021,
          77.5983672
        ],
        [
          12.9821412,
          77.5988597
        ]
      ]
    },
    {
      "algorithm": "Dijkstra",
      "time": 0.1523769999985234,
      "nodes": 20862,
      "distance": 10.142409548564686,
      "route": [
        [
          13.0274495,
          77.5434328
        ],
        [
          13.0272966,
          77.5436942
        ],
        [
          13.0270022,
          77.5435414
        ],
        [
          13.0267882,
          77.543901
        ],
        [
          13.0266639,
          77.5441183
        ],
        [
          13.0265475,
          77.5443205
        ],
        [
          13.02652,
          77.5443688
        ],
        [
          13.0264419,
          77.5445056
        ],
        [
          13.0262783,
          77.5447919
        ],
        [
          13.0261409,
          77.545034
        ],
        [
          13.0261054,
          77.5450986
        ],
        [
          13.0260108,
          77.545262
        ],
        [
          13.0249313,
          77.5471692
        ],
        [
          13.0247374,
          77.5475117
        ],
        [
          13.0247066,
          77.547572
        ],
        [
          13.0246136,
          77.5477353
        ],
        [
          13.0245653,
          77.5478201
        ],
        [
          13.0245012,
          77.5479328
        ],
        [
          13.0244568,
          77.5480082
        ],
        [
          13.0244128,
          77.548086
        ],
        [
          13.0243805,
          77.5481432
        ],
        [
          13.0242183,
          77.5484302
        ],
        [
          13.0241831,
          77.5484922
        ],
        [
          13.0241439,
          77.548561
        ],
        [
          13.0239562,
          77.5488912
        ],
        [
          13.0237829,
          77.5491463
        ],
        [
          13.0234939,
          77.5496389
        ],
        [
          13.0230509,
          77.5503516
        ],
        [
          13.0228045,
          77.5508058
        ],
        [
          13.0226969,
          77.5510277
        ],
        [
          13.0225022,
          77.5513199
        ],
        [
          13.0223589,
          77.5514832
        ],
        [
          13.0222094,
          77.5516361
        ],
        [
          13.0220275,
          77.5517794
        ],
        [
          13.0218485,
          77.5519049
        ],
        [
          13.0216343,
          77.552036
        ],
        [
          13.0210655,
          77.5523307
        ],
        [
          13.0197485,
          77.5530421
        ],
        [
          13.0195316,
          77.5531433
        ],
        [
          13.019371,
          77.5532075
        ],
        [
          13.0192211,
          77.5532574
        ],
        [
          13.0190504,
          77.553303
        ],
        [
          13.0178943,
          77.5535869
        ],
        [
          13.0177693,
          77.5536176
        ],
        [
          13.0172412,
          77.5537435
        ],
        [
          13.0169446,
          77.553794
        ],
        [
          13.0166951,
          77.5538253
        ],
        [
          13.0162882,
          77.5538613
        ],
        [
          13.0161467,
          77.5538709
        ],
        [
          13.0160489,
          77.5538828
        ],
        [
          13.0159637,
          77.5539138
        ],
        [
          13.0159,
          77.5539575
        ],
        [
          13.0158471,
          77.5540122
        ],
        [
          13.0156651,
          77.5542035
        ],
        [
          13.015608,
          77.5542919
        ],
        [
          13.015547,
          77.5544046
        ],
        [
          13.0155177,
          77.5544877
        ],
        [
          13.0155055,
          77.5545382
        ],
        [
          13.0154946,
          77.5545832
        ],
        [
          13.0154865,
          77.554739
        ],
        [
          13.0155011,
          77.5549491
        ],
        [
          13.0155207,
          77.555063
        ],
        [
          13.0155344,
          77.555143
        ],
        [
          13.0155858,
          77.5552981
        ],
        [
          13.0156628,
          77.5554694
        ],
        [
          13.0157848,
          77.5556735
        ],
        [
          13.0159736,
          77.5559295
        ],
        [
          13.0161611,
          77.5561139
        ],
        [
          13.0162957,
          77.5562294
        ],
        [
          13.0164109,
          77.5563145
        ],
        [
          13.0166404,
          77.5564571
        ],
        [
          13.0166867,
          77.5564859
        ],
        [
          13.0168603,
          77.5565106
        ],
        [
          13.0175219,
          77.5568519
        ],
        [
          13.0175723,
          77.5568779
        ],
        [
          13.0177497,
          77.5569808
        ],
        [
          13.0178988,
          77.5570595
        ],
        [
          13.0179531,
          77.5570922
        ],
        [
          13.0181111,
          77.5571766
        ],
        [
          13.0183171,
          77.5572971
        ],
        [
          13.0183944,
          77.5573265
        ],
        [
          13.018545,
          77.5573937
        ],
        [
          13.0186026,
          77.557431
        ],
        [
          13.0186212,
          77.557443
        ],
        [
          13.0186464,
          77.5574696
        ],
        [
          13.0186764,
          77.5575011
        ],
        [
          13.01874,
          77.5576107
        ],
        [
          13.0187692,
          77.557677
        ],
        [
          13.0187824,
          77.557709
        ],
        [
          13.0187775,
          77.5579212
        ],
        [
          13.0187737,
          77.5579378
        ],
        [
          13.0187112,
          77.5581177
        ],
        [
          13.0186639,
          77.5581887
        ],
        [
          13.01856,
          77.5583695
        ],
        [
          13.0184043,
          77.5586513
        ],
        [
          13.0182341,
          77.5588908
        ],
        [
          13.0181994,
          77.5589397
        ],
        [
          13.0180601,
          77.5590569
        ],
        [
          13.0176671,
          77.5597027
        ],
        [
          13.0171281,
          77.5605923
        ],
        [
          13.0165773,
          77.5615849
        ],
        [
          13.016062,
          77.5625188
        ],
        [
          13.0151584,
          77.5640534
        ],
        [
          13.0149021,
          77.5645232
        ],
        [
          13.0143864,
          77.5653925
        ],
        [
          13.014349,
          77.5654698
        ],
        [
          13.0142742,
          77.5656371
        ],
        [
          13.0142461,
          77.5657162
        ],
        [
          13.0142082,
          77.5658425
        ],
        [
          13.0141965,
          77.5659475
        ],
        [
          13.0141972,
          77.5660003
        ],
        [
          13.0142056,
          77.5662077
        ],
        [
          13.0143258,
          77.5676217
        ],
        [
          13.0143453,
          77.5677608
        ],
        [
          13.014366,
          77.5680793
        ],
        [
          13.0143945,
          77.5685165
        ],
        [
          13.0144851,
          77.56991
        ],
        [
          13.0144871,
          77.5699371
        ],
        [
          13.0145926,
          77.571349
        ],
        [
          13.0146256,
          77.5717912
        ],
        [
          13.0146546,
          77.5721798
        ],
        [
          13.0146671,
          77.5723464
        ],
        [
          13.0146715,
          77.5724063
        ],
        [
          13.0146756,
          77.5724617
        ],
        [
          13.0146854,
          77.5725927
        ],
        [
          13.014694,
          77.5727074
        ],
        [
          13.0146971,
          77.5727488
        ],
        [
          13.014704,
          77.5728407
        ],
        [
          13.0147061,
          77.5728808
        ],
        [
          13.0147699,
          77.5741014
        ],
        [
          13.0147862,
          77.5744368
        ],
        [
          13.0147893,
          77.5745002
        ],
        [
          13.0148051,
          77.5747475
        ],
        [
          13.0148153,
          77.5750631
        ],
        [
          13.014816,
          77.5750862
        ],
        [
          13.0148374,
          77.575762
        ],
        [
          13.0148452,
          77.5766071
        ],
        [
          13.0148423,
          77.5770005
        ],
        [
          13.0148268,
          77.5777181
        ],
        [
          13.0148101,
          77.5784883
        ],
        [
          13.0148056,
          77.5786958
        ],
        [
          13.014807,
          77.5790318
        ],
        [
          13.0148075,
          77.5791597
        ],
        [
          13.0148045,
          77.5794019
        ],
        [
          13.0148016,
          77.5796548
        ],
        [
          13.0147905,
          77.5799607
        ],
        [
          13.0147604,
          77.5805379
        ],
        [
          13.0147094,
          77.5815166
        ],
        [
          13.014673,
          77.5822314
        ],
        [
          13.0146705,
          77.5822757
        ],
        [
          13.0146536,
          77.5825754
        ],
        [
          13.0146185,
          77.5831427
        ],
        [
          13.0146019,
          77.583419
        ],
        [
          13.0145801,
          77.5836796
        ],
        [
          13.0145703,
          77.5837967
        ],
        [
          13.0145702,
          77.5838403
        ],
        [
          13.0145697,
          77.5839359
        ],
        [
          13.0145669,
          77.5841073
        ],
        [
          13.0145662,
          77.5841799
        ],
        [
          13.0145645,
          77.5845022
        ],
        [
          13.0145623,
          77.5847529
        ],
        [
          13.0145607,
          77.5849408
        ],
        [
          13.0145579,
          77.5852689
        ],
        [
          13.0145578,
          77.585278
        ],
        [
          13.0145375,
          77.5854593
        ],
        [
          13.0144891,
          77.5858376
        ],
        [
          13.014406,
          77.5864063
        ],
        [
          13.0143768,
          77.5865594
        ],
        [
          13.0143041,
          77.5868589
        ],
        [
          13.0142607,
          77.5869686
        ],
        [
          13.0141603,
          77.5872122
        ],
        [
          13.0141025,
          77.5873374
        ],
        [
          13.0139105,
          77.5877168
        ],
        [
          13.0137547,
          77.5879342
        ],
        [
          13.0135957,
          77.5880799
        ],
        [
          13.0135011,
          77.5881589
        ],
        [
          13.0132754,
          77.5883375
        ],
        [
          13.0128837,
          77.5886778
        ],
        [
          13.0117953,
          77.5894494
        ],
        [
          13.0115947,
          77.5895877
        ],
        [
          13.0105701,
          77.5902759
        ],
        [
          13.0101366,
          77.5905814
        ],
        [
          13.010025,
          77.5906561
        ],
        [
          13.0095286,
          77.5909738
        ],
        [
          13.0091024,
          77.5912466
        ],
        [
          13.0080864,
          77.59191
        ],
        [
          13.0078196,
          77.5920975
        ],
        [
          13.0075132,
          77.5922943
        ],
        [
          13.0073589,
          77.5923706
        ],
        [
          13.0066632,
          77.5928061
        ],
        [
          13.0066605,
          77.5928076
        ],
        [
          13.0062871,
          77.593014
        ],
        [
          13.0061524,
          77.5930741
        ],
        [
          13.0060671,
          77.5931142
        ],
        [
          13.00592,
          77.5931874
        ],
        [
          13.005805,
          77.5932256
        ],
        [
          13.0056163,
          77.5932782
        ],
        [
          13.0055173,
          77.5933072
        ],
        [
          13.0049879,
          77.5934514
        ],
        [
          13.0045096,
          77.5935832
        ],
        [
          13.0044641,
          77.5935957
        ],
        [
          13.0025857,
          77.5941777
        ],
        [
          13.0018764,
          77.5944004
        ],
        [
          13.0015048,
          77.5945171
        ],
        [
          13.0014563,
          77.5945315
        ],
        [
          12.9999623,
          77.594999
        ],
        [
          12.9976888,
          77.5956735
        ],
        [
          12.9972213,
          77.5958045
        ],
        [
          12.996209,
          77.5959395
        ],
        [
          12.9959296,
          77.595954
        ],
        [
          12.9957118,
          77.595984
        ],
        [
          12.9950408,
          77.5960927
        ],
        [
          12.9948669,
          77.5961137
        ],
        [
          12.9947799,
          77.5960977
        ],
        [
          12.9945497,
          77.5959841
        ],
        [
          12.9943169,
          77.595876
        ],
        [
          12.9942685,
          77.5958661
        ],
        [
          12.9942104,
          77.5958806
        ],
        [
          12.994152,
          77.5962241
        ],
        [
          12.9941208,
          77.5963919
        ],
        [
          12.9940894,
          77.5965051
        ],
        [
          12.9940353,
          77.5966565
        ],
        [
          12.9938347,
          77.5967279
        ],
        [
          12.9936324,
          77.5968779
        ],
        [
          12.9933705,
          77.5971645
        ],
        [
          12.9931565,
          77.5975674
        ],
        [
          12.9930127,
          77.597813
        ],
        [
          12.9929827,
          77.5978644
        ],
        [
          12.9929147,
          77.5980113
        ],
        [
          12.9929069,
          77.5981589
        ],
        [
          12.9929356,
          77.5982957
        ],
        [
          12.9929014,
          77.5984316
        ],
        [
          12.9928809,
          77.5985098
        ],
        [
          12.9923015,
          77.6000075
        ],
        [
          12.9922893,
          77.6000414
        ],
        [
          12.9918412,
          77.5999249
        ],
        [
          12.9907397,
          77.599624
        ],
        [
          12.9907063,
          77.599613
        ],
        [
          12.9905185,
          77.5995661
        ],
        [
          12.9904351,
          77.5995369
        ],
        [
          12.9897683,
          77.5993038
        ],
        [
          12.9894026,
          77.599176
        ],
        [
          12.9883347,
          77.5988027
        ],
        [
          12.9875395,
          77.5985247
        ],
        [
          12.9873539,
          77.5984275
        ],
        [
          12.9870229,
          77.598274
        ],
        [
          12.9867013,
          77.5981458
        ],
        [
          12.9863163,
          77.5979931
        ],
        [
          12.9861562,
          77.5979295
        ],
        [
          12.9856695,
          77.5977364
        ],
        [
          12.9852024,
          77.597551
        ],
        [
          12.984566,
          77.5972588
        ],
        [
          12.9845528,
          77.5972528
        ],
        [
          12.9845305,
          77.5972423
        ],
        [
          12.9845003,
          77.5972273
        ],
        [
          12.9844235,
          77.5972837
        ],
        [
          12.984327,
          77.597199
        ],
        [
          12.9841797,
          77.5971128
        ],
        [
          12.9841563,
          77.5970901
        ],
        [
          12.983979,
          77.5971038
        ],
        [
          12.9837064,
          77.5971058
        ],
        [
          12.98364,
          77.5971063
        ],
        [
          12.9834359,
          77.5971078
        ],
        [
          12.9831307,
          77.5971101
        ],
        [
          12.9828705,
          77.5971408
        ],
        [
          12.9828464,
          77.5971431
        ],
        [
          12.9827271,
          77.5971513
        ],
        [
          12.9826708,
          77.5972842
        ],
        [
          12.9826053,
          77.5974734
        ],
        [
          12.9824663,
          77.597875
        ],
        [
          12.982415,
          77.5980314
        ],
        [
          12.9823021,
          77.5983672
        ],
        [
          12.9821412,
          77.5988597
        ]
      ]
    }
  ]
}